{
  "micrositeBackImageOpacity": 0.4,
  "buttonBorderStyle": "two",
  "customFooter": "Keep calm & drink coffee",
  "shortLinkId": {
    "claimable": false,
    "banned": false,
    "preGenerated": false,
    "target": "https://app-dev.theqr.link/qr/2eebefcb-b0a3-4081-ba9d-609e0c8d422e",
    "updatedAt": "2023-03-20T23:30:35.996Z",
    "userId": "eea77e04-08d8-4277-8ca2-b8ba8744a635",
    "createdAt": "2023-03-20T23:30:35.995Z",
    "visitCount": 15,
    "address": "Fz3fWb",
    "paused": false,
    "type": "qr_link"
  },
  "buttonBorderColors": "#3e2723|#f2eceb",
  "foregndImg": [
    {
      "name": "businessCoffeeMain2.png",
      "Key": "links/design/businessCoffeeMain2.png"
    }
  ],
  "sectionTitleFontSize": "large",
  "buttonBorderWeight": "weight",
  "custom": [
    {
      "data": {
        "iconSize": "medium",
        "socialsOnlyIcons": true,
        "hideHeadLine": true,
        "socials": [
          {
            "value": "https://example.com",
            "network": "instagram"
          },
          {
            "value": "https://example.com",
            "network": "twitter"
          },
          {
            "value": "https://example.com",
            "network": "pinterest"
          }
        ],
        "bottomSpacing": "medium",
        "topSpacing": "medium"
      },
      "component": "socials"
    },
    {
      "data": {
        "titleAbout": "Brew Haven Shop",
        "bottomSpacing": "wide",
        "descriptionAbout": "Experience the perfect blend of quality coffee and cozy ambiance at our shop."
      },
      "component": "title"
    },
    {
      "data": {
        "links": [
          {
            "link": "https://example.com",
            "label": "Website"
          },
          {
            "link": "https://example.com",
            "label": "Digital Menu"
          },
          {
            "link": "https://example.com",
            "label": "Order Online"
          },
          {
            "link": "https://example.com",
            "label": "Youtube channel"
          }
        ],
        "hideHeadLine": true
      },
      "component": "links"
    }
  ],
  "buttonsOpacity": 0.47,
  "subtitlesFontStyle": "b",
  "background": {
    "x": 0,
    "y": 0,
    "file": null,
    "type": "solid",
    "opacity": 50,
    "size": 1
  },
  "buttonsFontStyle": "b",
  "buttonBorderType": "double",
  "qrType": "link",
  "image": "",
  "userId": "eea77e04-08d8-4277-8ca2-b8ba8744a635",
  "titlesFontStyle": "b",
  "footerKind": "custom",
  "secondary": "#d7ccc8",
  "sectionDescFontStyle": "",
  "qrName": "Coffe",
  "messagesFontStyle": "",
  "createdAt": "2023-03-20T23:30:35.997Z",
  "layout": "nobanner",
  "profileImageSize": "medium",
  "profileImageVertical": "upper",
  "sectionTitleFontStyle": "b",
  "isDynamic": true,
  "updatedAt": "2023-03-22T19:32:56.654Z",
  "micrositeBackImage": [
    {
      "name": "businessCoffeeBg2.png",
      "Key": "links/design/businessCoffeeBg2.png"
    }
  ],
  "backgroundType": "image",
  "globalFont": "Comic Sans",
  "primary": "#3e2723"
}